simple_ddl_generator/__init__.py
simple_ddl_generator/core.py
simple_ddl_generator/generator.py
simple_ddl_generator/models_data.py
simple_ddl_generator/templates/common.jinja2
simple_ddl_generator/templates/table/before_table.jinja2
simple_ddl_generator/templates/table/column.jinja2
simple_ddl_generator/templates/table/column_base.jinja2
simple_ddl_generator/templates/table/create_table.jinja2
simple_ddl_generator/templates/table/table_properties.jinja2
simple_ddl_generator/templates/type/create_type.jinja2
simple_ddl_generator/type_converter.py
simple_ddl_generator-0.4.1.dist-info/LICENSE
simple_ddl_generator-0.4.1.dist-info/WHEEL
simple_ddl_generator-0.4.1.dist-info/METADATA
simple_ddl_generator-0.4.1.dist-info/RECORD
