Metadata-Version: 2.1
Name: simple-ddl-generator
Version: 0.4.1
Summary: Library to generate DDL for different dialects
Author: Iuliia Volkova
Author-email: xnuinside@gmail.com
Requires-Python: >=3.6.2,<4.0
Classifier: Programming Language :: PL/SQL
Classifier: Programming Language :: Python :: 3
Classifier: Programming Language :: Python :: 3.6
Classifier: Programming Language :: Python :: 3.7
Classifier: Programming Language :: Python :: 3.8
Classifier: Programming Language :: Python :: 3.9
Classifier: Programming Language :: SQL
Classifier: Topic :: Software Development
Classifier: Topic :: Software Development :: Libraries
Classifier: Topic :: Software Development :: Libraries :: Python Modules
Classifier: Topic :: Utilities
Requires-Dist: jinja2 (>=3.0.3,<4.0.0)
Requires-Dist: table-meta (==0.3.2)
